<?xml version="1.0" encoding="UTF-8" ?>
<pageDefinition xmlns="http://xmlns.oracle.com/adfm/uimodel"
                version="11.1.1.64.93" id="untitled1PageDef1"
                Package="com.lbspak.view.pageDefs">
  <parameters/>
  <executables>
    <variableIterator id="variables"/>
    <iterator Binds="TestPivotTableView1" RangeSize="-1"
              DataControl="LBSAppModuleDataControl"
              id="TestPivotTableView1Iterator"/>
  </executables>
  <bindings>
    <pivotTable IterBinding="TestPivotTableView1Iterator"
                id="TestPivotTableView1"
                xmlns="http://xmlns.oracle.com/adfm/dvt">
      <pivotTableDataMap>
        <columns>
          <data>
            <item value="Duration"/>
          </data>
          <item value="Day"/>
        </columns>
        <rows>
          <item value="Spot"/>
        </rows>
      </pivotTableDataMap>
    </pivotTable>
  </bindings>
</pageDefinition>
